{
  "subject_property": {
    "Address": "123 Main St, Springfield, IL 62704",
    "Proximity_to_Subject": "Subject",
    "Sale_price": 350000,
    "Gross_Living_Area": 2200,
    "Verification_Source": "ZILLOW",
    "Date_of_Sale_Time": "2022-05-10",
    "Beds": 4,
    "Baths": 3,
    "Lot_Area": 10000,
    "Design_and_Appeal": "",
    "Year_Built": 2005,
    "Garage_Carport": "2",
    "Porch": "Covered Front Porch",
    "Patio_Deck": "Rear Deck",
    "Fireplaces": 1,
    "Fence": "Wood Privacy Fence",
    "Pool": "No",
    "Room_Count": 9,
    "Price_per_Square_Foot": "",
    "Living_Adjustment": 0,
    "Age": "",
    "Quality_of_Construction": "",
    "Improvements_Value": 250000,
    "Land_Value": 100000,
    "Location": "",
    "View": "",
    "Condition": "",
    "Above_Grade": "",
    "Sales_or_Financing_Concessions": "None",
    "Leasehold_or_Fee_Simple": "Fee Simple",
    "Rooms_Below_Grade": 2,
    "Functional_Utility": "Adequate",
    "Heat_Cooling": "Central HVAC",
    "Energy_Efficient_Items": ["Double Pane Windows", "Insulated Doors"],
    "Basement_and_Finished": "Full Basement - 50% Finished",
    "Site": "Level, Interior Lot"
  },
  "comparables": [
    {
      "Address": "101 Oak St, Springfield, IL 62704",
      "Proximity_to_Subject": "0.3",
      "Sale_price": 345000,
      "Gross_Living_Area": 2150,
      "Verification_Source": "ZILLOW",
      "Date_of_Sale_Time": "2024-03-15",
      "Beds": 4,
      "Baths": 3,
      "Lot_Area": 9500,
      "Design_and_Appeal": "",
      "Year_Built": 2006,
      "Garage_Carport": "2",
      "Porch": "Open Front Porch",
      "Patio_Deck": "Rear Patio",
      "Fireplaces": 1,
      "Fence": "Chain-link",
      "Pool": "No",
      "Room_Count": 9,
      "Price_per_Square_Foot": "",
      "Living_Adjustment": -5000,
      "Age": 18,
      "Quality_of_Construction": "",
      "Improvements_Value": 240000,
      "Land_Value": 105000,
      "Location": "",
      "View": "",
      "Condition": "",
      "Above_Grade": "",
      "Sales_or_Financing_Concessions": "Seller Paid Closing Costs",
      "Leasehold_or_Fee_Simple": "Fee Simple",
      "Rooms_Below_Grade": 1,
      "Functional_Utility": "Typical",
      "Heat_Cooling": "Central HVAC",
      "Energy_Efficient_Items": ["Programmable Thermostat"],
      "Basement_and_Finished": "Full Basement - 40% Finished",
      "Site": "Interior Lot"
    },
    {
      "Address": "205 Pine St, Springfield, IL 62704",
      "Proximity_to_Subject": "0.5",
      "Sale_price": 360000,
      "Gross_Living_Area": 2300,
      "Verification_Source": "ZILLOW",
      "Date_of_Sale_Time": "2024-01-22",
      "Beds": 4,
      "Baths": 3,
      "Lot_Area": 11000,
      "Design_and_Appeal": "",
      "Year_Built": 2008,
      "Garage_Carport": "3",
      "Porch": "Covered",
      "Patio_Deck": "Large Rear Deck",
      "Fireplaces": 2,
      "Fence": "Wood",
      "Pool": "Yes - Above Ground",
      "Room_Count": 10,
      "Price_per_Square_Foot": "",
      "Living_Adjustment": 10000,
      "Age": "",
      "Quality_of_Construction": "",
      "Improvements_Value": 270000,
      "Land_Value": 90000,
      "Location": "",
      "View": "",
      "Condition": "",
      "Above_Grade": "",
      "Sales_or_Financing_Concessions": "None",
      "Leasehold_or_Fee_Simple": "Fee Simple",
      "Rooms_Below_Grade": 2,
      "Functional_Utility": "Above Average",
      "Heat_Cooling": "Central HVAC",
      "Energy_Efficient_Items": ["Solar Panels", "Energy Star Appliances"],
      "Basement_and_Finished": "Partial Basement - 60% Finished",
      "Site": ""
    },
    {
      "Address": "315 Maple Ave, Springfield, IL 62704",
      "Proximity_to_Subject": "0.4",
      "Sale_price": 330000,
      "Gross_Living_Area": 2100,
      "Verification_Source": "ZILLOW",
      "Date_of_Sale_Time": "2023-12-05",
      "Beds": 3,
      "Baths": 2,
      "Lot_Area": 8700,
      "Design_and_Appeal": "",
      "Year_Built": 2000,
      "Garage_Carport": "2",
      "Porch": "None",
      "Patio_Deck": "Rear Patio",
      "Fireplaces": 0,
      "Fence": "None",
      "Pool": "No",
      "Room_Count": 7,
      "Price_per_Square_Foot": "",
      "Living_Adjustment": -20000,
      "Age": "",
      "Quality_of_Construction": "",
      "Improvements_Value": 220000,
      "Land_Value": 110000,
      "Location": "",
      "View": "",
      "Condition": "",
      "Above_Grade": "",
      "Sales_or_Financing_Concessions": "Conventional Financing",
      "Leasehold_or_Fee_Simple": "Fee Simple",
      "Rooms_Below_Grade": 1,
      "Functional_Utility": "Adequate",
      "Heat_Cooling": "Central Air",
      "Energy_Efficient_Items": ["Ceiling Fans"],
      "Basement_and_Finished": "Crawlspace",
      "Site": ""
    },
    {
      "Address": "420 Cedar Ln, Springfield, IL 62704",
      "Proximity_to_Subject": "0.6 miles SE",
      "Sale_price": 355000,
      "Gross_Living_Area": 2250,
      "Verification_Source": "ZILLOW",
      "Date_of_Sale_Time": "2024-02-12",
      "Beds": 4,
      "Baths": 3,
      "Lot_Area": 9800,
      "Design_and_Appeal": "",
      "Year_Built": 2007,
      "Garage_Carport": "2",
      "Porch": "Front Covered Porch",
      "Patio_Deck": "Wood Deck",
      "Fireplaces": 1,
      "Fence": "Wood",
      "Pool": "No",
      "Room_Count": 9,
      "Price_per_Square_Foot": "",
      "Living_Adjustment": 0,
      "Age": "",
      "Quality_of_Construction": "",
      "Improvements_Value": 245000,
      "Land_Value": 110000,
      "Location": "",
      "View": "",
      "Condition": "",
      "Above_Grade": "",
      "Sales_or_Financing_Concessions": "Seller Paid Closing Costs",
      "Leasehold_or_Fee_Simple": "Fee Simple",
      "Rooms_Below_Grade": 2,
      "Functional_Utility": "Typical",
      "Heat_Cooling": "Gas Furnace, Central Air",
      "Energy_Efficient_Items": ["Double Pane Windows"],
      "Basement_and_Finished": "Full Basement - Unfinished",
      "Site": "Interior Lot, Flat"
    },
    {
      "Address": "530 Birch Dr, Springfield, IL 62704",
      "Proximity_to_Subject": "0.8",
      "Sale_price": 365000,
      "Gross_Living_Area": 2400,
      "Verification_Source": "ZILLOW",
      "Date_of_Sale_Time": "2024-06-01",
      "Beds": 5,
      "Baths": 3,
      "Lot_Area": 12000,
      "Design_and_Appeal": "",
      "Year_Built": 2010,
      "Garage_Carport": "2",
      "Porch": "Wraparound Porch",
      "Patio_Deck": "Rear Deck with Pergola",
      "Fireplaces": 1,
      "Fence": "Vinyl",
      "Pool": "No",
      "Room_Count": 11,
      "Price_per_Square_Foot": "",
      "Living_Adjustment": 15000,
      "Age": "",
      "Quality_of_Construction": "",
      "Improvements_Value": 280000,
      "Land_Value": 85000,
      "Location": "",
      "View": "",
      "Condition": "",
      "Above_Grade": "",
      "Sales_or_Financing_Concessions": "None",
      "Leasehold_or_Fee_Simple": "Fee Simple",
      "Rooms_Below_Grade": 3,
      "Functional_Utility": "Above Average",
      "Heat_Cooling": "High Efficiency HVAC",
      "Energy_Efficient_Items": ["Solar Panels", "Energy Star Windows", "Tankless Water Heater"],
      "Basement_and_Finished": "Full Basement - 80% Finished",
      "Site": ""
    }
  ]
}
